medgnn/__init__.py
medgnn/__init__.pyi
medgnn/medgnn/__init__.py
medgnn/medgnn/__init__.pyi
medgnn/medgnn/knn.py
medgnn/medgnn/model.py
medgnn/util/__init__.py
medgnn/util/load.py
medgnn/util/metrics.py
medgnn/util/optim.py
medgnn/util/scatter.py
medgnn/util/util.py
medgnn_lib-0.1.12.dist-info/METADATA
medgnn_lib-0.1.12.dist-info/WHEEL
medgnn_lib-0.1.12.dist-info/top_level.txt
medgnn_lib-0.1.12.dist-info/RECORD
